pysma_plus-0.3.24.dist-info/licenses/LICENSE
pysmaplus/__init__.py
pysmaplus/const.py
pysmaplus/const_webconnect.py
pysmaplus/definitions_em.py
pysmaplus/definitions_ennexos.py
pysmaplus/definitions_speedwire.py
pysmaplus/definitions_webconnect.py
pysmaplus/device.py
pysmaplus/device_em.py
pysmaplus/device_ennexos.py
pysmaplus/device_shm2.py
pysmaplus/device_speedwire.py
pysmaplus/device_speedwire2.py
pysmaplus/device_webconnect.py
pysmaplus/discovery.py
pysmaplus/exceptions.py
pysmaplus/helpers.py
pysmaplus/sensor.py
pysmaplus/semp/RendererStatusPage.py
pysmaplus/semp/SEMPhttpd.py
pysmaplus/semp/__init__.py
pysmaplus/semp/const.py
pysmaplus/semp/device.py
pysmaplus/semp/sempxsd.py
pysmaplus/semp/ssdp.py
pysma_plus-0.3.24.dist-info/METADATA
pysma_plus-0.3.24.dist-info/WHEEL
pysma_plus-0.3.24.dist-info/top_level.txt
pysma_plus-0.3.24.dist-info/zip-safe
pysma_plus-0.3.24.dist-info/RECORD
