Metadata-Version: 2.4
Name: pysma-plus
Version: 0.3.24
Summary: Library to interface SMA Devices via Speedwire, WebConnect, EnnexOS and Energy Meter Protocol
Home-page: https://github.com/littleyoda/pysma
Download-URL: https://github.com/littleyoda/pysma/tarball/0.3.24
Author: Sven Bursch-Osewold, Johann Kellerman and other
Author-email: Sven Bursch-Osewold <sb_pysma@bursch.com>, Johann Kellerman <kellerza@gmail.com>
License-Expression: MIT
Project-URL: Homepage, https://github.com/littleyoda/pysma
Classifier: Programming Language :: Python
Classifier: Programming Language :: Python :: 3
Requires-Python: >=3.9
License-File: LICENSE
Requires-Dist: aiohttp<4,>3.3
Requires-Dist: attrs>18
Requires-Dist: jmespath<2
Requires-Dist: dataclasses-struct<1.0,>0.8
Requires-Dist: untangle>=1.2.1
Requires-Dist: xmlschema>=3.3.0
Requires-Dist: pymodbus<3.12,>=3.11.0
Dynamic: author
Dynamic: download-url
Dynamic: home-page
Dynamic: license-file
Dynamic: requires-python
